odoo/addons/web_widget_char_size/README.rst
odoo/addons/web_widget_char_size/__init__.py
odoo/addons/web_widget_char_size/__manifest__.py
odoo/addons/web_widget_char_size/i18n/web_widget_char_size.pot
odoo/addons/web_widget_char_size/readme/DESCRIPTION.rst
odoo/addons/web_widget_char_size/static/description/icon.png
odoo/addons/web_widget_char_size/static/description/index.html
odoo/addons/web_widget_char_size/static/src/js/char_widget.js
odoo/addons/web_widget_char_size/views/assets.xml
odoo14_addon_web_widget_char_size-14.0.1.0.1.dist-info/METADATA
odoo14_addon_web_widget_char_size-14.0.1.0.1.dist-info/WHEEL
odoo14_addon_web_widget_char_size-14.0.1.0.1.dist-info/top_level.txt
odoo14_addon_web_widget_char_size-14.0.1.0.1.dist-info/RECORD
